robosuite_models/__init__.py
robosuite_models/utils.py
robosuite_models/assets/.DS_Store
robosuite_models/assets/bases/.DS_Store
robosuite_models/assets/bases/aloha_mount.xml
robosuite_models/assets/bases/meshes/aloha_mount/angled_extrusion.stl
robosuite_models/assets/bases/meshes/aloha_mount/corner_bracket.stl
robosuite_models/assets/bases/meshes/aloha_mount/d405_solid.stl
robosuite_models/assets/bases/meshes/aloha_mount/extrusion_1000.stl
robosuite_models/assets/bases/meshes/aloha_mount/extrusion_1220.stl
robosuite_models/assets/bases/meshes/aloha_mount/extrusion_150.stl
robosuite_models/assets/bases/meshes/aloha_mount/extrusion_2040_1000.stl
robosuite_models/assets/bases/meshes/aloha_mount/extrusion_2040_880.stl
robosuite_models/assets/bases/meshes/aloha_mount/extrusion_600.stl
robosuite_models/assets/bases/meshes/aloha_mount/overhead_mount.stl
robosuite_models/assets/bases/meshes/aloha_mount/small_meta_table_diffuse.png
robosuite_models/assets/bases/meshes/aloha_mount/tablelegs.obj
robosuite_models/assets/bases/meshes/aloha_mount/tabletop.obj
robosuite_models/assets/bases/meshes/aloha_mount/wormseye_mount.stl
robosuite_models/assets/grippers/.DS_Store
robosuite_models/assets/grippers/ability_left_hand.xml
robosuite_models/assets/grippers/ability_right_hand.xml
robosuite_models/assets/grippers/aloha_gripper.xml
robosuite_models/assets/grippers/g1_three_finger_left_gripper.xml
robosuite_models/assets/grippers/g1_three_finger_right_gripper.xml
robosuite_models/assets/grippers/pr2_gripper.xml
robosuite_models/assets/grippers/schunk_svh_left_hand.xml
robosuite_models/assets/grippers/schunk_svh_right_hand.xml
robosuite_models/assets/grippers/umi_gripper.xml
robosuite_models/assets/grippers/yumi_left_gripper.xml
robosuite_models/assets/grippers/yumi_right_gripper.xml
robosuite_models/assets/grippers/z1_gripper.xml
robosuite_models/assets/grippers/meshes/ability_hand/collision/FB_palm_ref.obj
robosuite_models-1.0.0.dist-info/LICENSE
robosuite_models-1.0.0.dist-info/METADATA
robosuite_models-1.0.0.dist-info/WHEEL
robosuite_models-1.0.0.dist-info/eager_resources.txt
robosuite_models-1.0.0.dist-info/top_level.txt
robosuite_models-1.0.0.dist-info/RECORD
