Metadata-Version: 2.1
Name: robosuite_models
Version: 1.0.0
Summary: A collection of robot models for robosuite simulation.
Home-page: https://github.com/ARISE-Initiative/robosuite_models
Author: Yifeng Zhu
Author-email: robosuite core team members <yifeng.zhu@utexas.edu>
Project-URL: Homepage, https://github.com/ARISE-Initiative/robosuite_models
Project-URL: Issues, https://github.com/ARISE-Initiative/robosuite_models/issues
Classifier: Programming Language :: Python :: 3
Classifier: License :: OSI Approved :: MIT License
Classifier: Operating System :: OS Independent
Requires-Python: >=3
License-File: LICENSE
